neutrinomass/__init__.py
neutrinomass/database/database.py
neutrinomass/database/json_serialiser.py
neutrinomass/database/closures.py
neutrinomass/database/__init__.py
neutrinomass/database/export.py
neutrinomass/database/terms.p
neutrinomass/database/utils.py
neutrinomass/database/export_test.py
neutrinomass/database/database_test.py
neutrinomass/database/closures_test.py
neutrinomass/database/exotics.p
neutrinomass/database/democratic.p
neutrinomass/database/operators.py
neutrinomass/database/heavyloops.py
neutrinomass/analysis/__init__.py
neutrinomass/analysis/utils.py
neutrinomass/analysis/flavour_anomalies.py
neutrinomass/completions/tikzfeynman.py
neutrinomass/completions/topologies.py
neutrinomass/completions/__init__.py
neutrinomass/completions/core.py
neutrinomass/completions/deriv_operators.p
neutrinomass/completions/core_test.py
neutrinomass/completions/completions.py
neutrinomass/completions/d9.py
neutrinomass/completions/utils.py
neutrinomass/completions/operators.p
neutrinomass/completions/operators_test.py
neutrinomass/completions/operators.py
neutrinomass/completions/completions_test.py
neutrinomass/completions/topology_data/diagrams/5s4f_108.png
neutrinomass/completions/topology_data/diagrams/5s4f_134.png
neutrinomass/completions/topology_data/diagrams/5s4f_120.png
neutrinomass/completions/topology_data/diagrams/5s2f_19.png
neutrinomass/completions/topology_data/diagrams/5s4f_242.png
neutrinomass/completions/topology_data/diagrams/5s4f_256.png
neutrinomass/completions/topology_data/diagrams/5s4f_48.png
neutrinomass/completions/topology_data/diagrams/5s4f_74.png
neutrinomass/completions/topology_data/diagrams/5s4f_60.png
neutrinomass/completions/topology_data/diagrams/6s2f_39.png
neutrinomass/completions/topology_data/diagrams/6s2f_11.png
neutrinomass/completions/topology_data/diagrams/6s2f_10.png
neutrinomass/completions/topology_data/diagrams/6s2f_38.png
neutrinomass-1.0.1.dist-info/RECORD
neutrinomass-1.0.1.dist-info/metadata.json
neutrinomass-1.0.1.dist-info/WHEEL
neutrinomass-1.0.1.dist-info/DESCRIPTION.rst
neutrinomass-1.0.1.dist-info/top_level.txt
neutrinomass-1.0.1.dist-info/METADATA
