Metadata-Version: 2.0
Name: neutrinomass
Version: 1.0.1
Summary: Code behind arXiv:20xx.xxxxx.
Home-page: https://github.com/johngarg/neutrinomass
Author: John Gargalionis
Author-email: garj@student.unimelb.edu.au
License: MIT
Platform: UNKNOWN
Classifier: Programming Language :: Python :: 3
Classifier: License :: OSI Approved :: MIT License
Classifier: Operating System :: OS Independent
Requires-Python: >=3.6
Requires-Dist: matplotlib (>=3.0.2)
Requires-Dist: pytest (>=3.8.0)
Requires-Dist: basisgen (>=1.0.1)
Requires-Dist: networkx (>=2.2)
Requires-Dist: sympy (==1.2)
Requires-Dist: alive-progress (>=1.5.1)
Requires-Dist: matchpy (>=0.5.2)
Requires-Dist: pandas (>=1.1.2)
